{
  "founded": "",
  "employees": "",
  "logo": "/img/company/mobiltel.svg",
  "careers": "",
  "headquarters": "",
  "description": "",
  "internship": "",
  "tags": [],
  "remote": "",
  "name": "Mobiltel",
  "contact": {
    "web": "https://mobiltel.com.tr",
    "phone": "",
    "email": "",
    "address": ""
  },
  "sector": "",
  "social": {
    "linkedin": "https://linkedin.com/company/mobilteliletisim",
    "twitter": "",
    "facebook": "https://facebook.com/mobilteliletisim",
    "instagram": "https://instagram.com/mobilteltr",
    "youtube": "",
    "x": "https://x.com/mobilteltr"
  }
}