{
  "founded": "",
  "employees": "",
  "careers": "",
  "headquarters": "Şişli, İstanbul",
  "description": "",
  "internship": "",
  "tags": [],
  "remote": "",
  "name": "Bilkur",
  "contact": {
    "web": "https://bilkur.com.tr",
    "phone": "",
    "email": "",
    "address": ""
  },
  "sector": [
    "BT Hizmetleri ve BT Danışmanlığı"
  ],
  "social": {
    "linkedin": "https://linkedin.com/company/bilkur",
    "twitter": "",
    "facebook": "https://facebook.com/BilkurBarkodCozumleri",
    "instagram": "https://instagram.com/bilkurbarkod",
    "youtube": "https://youtube.com/@bilkur",
    "x": "https://x.com/BilkurBarkod"
  },
  "logo": "img/company/bilkur.png",
  "about": "Bilkur Bilgisayar San. ve Tic. Ltd. Şti.",
  "tagline": "Barkod Çözümlerinde Aklın Yolu \"BİLKUR\""
}