{
  "founded": "",
  "employees": "",
  "careers": "",
  "headquarters": "",
  "description": "",
  "internship": "",
  "tags": [],
  "remote": "",
  "name": "Obss",
  "contact": {
    "web": "https://obss.tech/en/",
    "phone": "",
    "email": "",
    "address": ""
  },
  "sector": "",
  "social": {
    "linkedin": "https://linkedin.com/company/obss",
    "twitter": "",
    "facebook": "https://facebook.com/obss.com.tr",
    "instagram": "https://instagram.com/obss.tech",
    "youtube": "",
    "x": "https://x.com/obsstech"
  },
  "logo": "img/company/obss.png"
}