{
    "name": "Rivo",
    "logo": "/img/company/rivo.svg",
    "web": "https://rivo.com.tr",
    "description": "",
    "sector": "",
    "founded": "",
    "employees": "",
    "headquarters": "",
    "tags": [],
    "products": [],
    "careers": "",
    "internship": "",
    "remote": "",
    "contact": {
        "email": "",
        "phone": "",
        "address": ""
    },
    "social": {
        "linkedin": "",
        "twitter": "",
        "facebook": "",
        "instagram": "",
        "youtube": ""
    }
}
